mosaic/ConvertToCSV.py
mosaic/SingleChannelAnalysis.py
mosaic/__init__.py
mosaic/_version.py
mosaic/abfTrajIO.py
mosaic/adept.py
mosaic/adept2State.py
mosaic/besselLowpassFilter.py
mosaic/binTrajIO.py
mosaic/commonExceptions.py
mosaic/convolutionFilter.py
mosaic/cusumPlus.py
mosaic/errors.py
mosaic/eventSegment.py
mosaic/metaEventPartition.py
mosaic/metaEventProcessor.py
mosaic/metaIOFilter.py
mosaic/metaMDIO.py
mosaic/metaTrajIO.py
mosaic/mosaicSetup.py
mosaic/pproc.py
mosaic/qdfTrajIO.py
mosaic/readGlobalSettings.py
mosaic/settings.py
mosaic/singleStepEvent.py
mosaic/sqlite3MDIO.py
mosaic/tsvTrajIO.py
mosaic/waveletDenoiseFilter.py
mosaic/zmqIO.py
mosaic/zmqWorker.py
mosaic/abf/__init__.py
mosaic/abf/abf.py
mosaic/apps/ConvertTrajIO.py
mosaic/apps/SingleChannelAnalysis.py
mosaic/apps/__init__.py
mosaic/filters/__init__.py
mosaic/filters/besselLowpassFilter.py
mosaic/filters/convolutionFilter.py
mosaic/filters/metaIOFilter.py
mosaic/filters/waveletDenoiseFilter.py
mosaic/mdio/__init__.py
mosaic/mdio/metaMDIO.py
mosaic/mdio/sqlite3MDIO.py
mosaic/partition/__init__.py
mosaic/partition/eventSegment.py
mosaic/partition/metaEventPartition.py
mosaic/process/__init__.py
mosaic/process/adept.py
mosaic/process/adept2State.py
mosaic/process/cusumPlus.py
mosaic/process/metaEventProcessor.py
mosaic/qdf/__init__.py
mosaic/qdf/readqdf.py
mosaic/tests/__init__.py
mosaic/tests/adept2State_Test.py
mosaic/tests/adept_Test.py
mosaic/tests/algorithmCommon.py
mosaic/tests/apps_Test.py
mosaic/tests/cusum_Test.py
mosaic/tests/eventPartitionCommon.py
mosaic/tests/eventPartitionParallel_Test.py
mosaic/tests/eventPartition_Test.py
mosaic/tests/import_Tests.py
mosaic/tests/mdio_Test.py
mosaic/tests/test_adept.py
mosaic/tests/test_adept2state.py
mosaic/tests/test_apps.py
mosaic/tests/test_cusum.py
mosaic/tests/test_eventPartition.py
mosaic/tests/test_import.py
mosaic/tests/test_mdio.py
mosaic/tests/test_trajio.py
mosaic/tests/testutil.py
mosaic/tests/trajio_Test.py
mosaic_nist-2.4.dist-info/LICENSE.rst
mosaic_nist-2.4.dist-info/METADATA
mosaic_nist-2.4.dist-info/WHEEL
mosaic_nist-2.4.dist-info/top_level.txt
mosaic_nist-2.4.dist-info/RECORD
