Metadata-Version: 2.1
Name: mosaic-nist
Version: 2.4
Summary: A Modular Single-Molecule Analysis Interface.
Home-page: https://pages.nist.gov/mosaic/
Author: National Institute of Standards and Technology (NIST)
Author-email: arvind.balijepalli@nist.gov
Maintainer: Arvind Balijepalli
Maintainer-email: arvind.balijepalli@nist.gov
License: US Government Open Source
Project-URL: Bug Tracker, https://github.com/usnistgov/mosaic/issues
Keywords: nanopore timeseries single-molecule data-analysis
Platform: MacOS
Platform: Windows
Platform: Linux
Classifier: Development Status :: 5 - Production/Stable
Classifier: Intended Audience :: Developers
Classifier: Topic :: Scientific/Engineering :: Bio-Informatics
Classifier: Programming Language :: Python :: 3
Classifier: Operating System :: OS Independent
Requires-Python: >=3.8
License-File: LICENSE.rst
Requires-Dist: cython (==0.29.32)
Requires-Dist: pandas (==1.5.2)
Requires-Dist: lmfit (==1.1.0)
Requires-Dist: uncertainties (==3.1.7)
Requires-Dist: PyWavelets (==1.4.1)
Requires-Dist: pytest (==7.2.2)
Requires-Dist: coverage (==6.5.0)
Requires-Dist: codecov (==2.1.12)
Requires-Dist: pytest-cov (==4.0.0)
Requires-Dist: pyinstaller (==5.6.2)
Requires-Dist: numpy (==1.23.5)
Requires-Dist: scipy (==1.9.3)
Requires-Dist: pyabf (==2.3.7)
Requires-Dist: docutils (==0.19)
Requires-Dist: flask (==2.2.2)
Requires-Dist: gunicorn (==20.1.0)
Provides-Extra: test
Requires-Dist: pytest ; extra == 'test'
Requires-Dist: pytest-cov ; extra == 'test'
Requires-Dist: coverage ; extra == 'test'
